platform_plugin_aspects/__init__.py
platform_plugin_aspects/apps.py
platform_plugin_aspects/signals.py
platform_plugin_aspects/tasks.py
platform_plugin_aspects/urls.py
platform_plugin_aspects/utils.py
platform_plugin_aspects/views.py
platform_plugin_aspects/waffle.py
platform_plugin_aspects/xblock.py
platform_plugin_aspects/extensions/__init__.py
platform_plugin_aspects/extensions/filters.py
platform_plugin_aspects/management/__init__.py
platform_plugin_aspects/management/commands/__init__.py
platform_plugin_aspects/management/commands/dump_data_to_clickhouse.py
platform_plugin_aspects/management/commands/load_test_tracking_events.py
platform_plugin_aspects/management/commands/monitor_load_test_tracking.py
platform_plugin_aspects/settings/__init__.py
platform_plugin_aspects/settings/common.py
platform_plugin_aspects/settings/production.py
platform_plugin_aspects/sinks/__init__.py
platform_plugin_aspects/sinks/base_sink.py
platform_plugin_aspects/sinks/course_enrollment_sink.py
platform_plugin_aspects/sinks/course_overview_sink.py
platform_plugin_aspects/sinks/external_id_sink.py
platform_plugin_aspects/sinks/serializers.py
platform_plugin_aspects/sinks/tag_sink.py
platform_plugin_aspects/sinks/user_profile_sink.py
platform_plugin_aspects/sinks/user_retire_sink.py
platform_plugin_aspects/static/css/superset.css
platform_plugin_aspects/static/html/superset.html
platform_plugin_aspects/static/html/superset_student.html
platform_plugin_aspects/static/js/embed_dashboard.js
platform_plugin_aspects/static/js/install_required.js
platform_plugin_aspects/static/js/superset.js
platform_plugin_aspects/templates/instructor_dashboard/aspects.html
platform_plugin_aspects-1.1.2.dist-info/licenses/LICENSE
platform_plugin_aspects-1.1.2.dist-info/METADATA
platform_plugin_aspects-1.1.2.dist-info/WHEEL
platform_plugin_aspects-1.1.2.dist-info/entry_points.txt
platform_plugin_aspects-1.1.2.dist-info/top_level.txt
platform_plugin_aspects-1.1.2.dist-info/RECORD
