Metadata-Version: 2.4
Name: platform-plugin-aspects
Version: 1.1.2
Summary: Aspects plugins for edx-platform
Home-page: https://github.com/openedx/platform-plugin-aspects
Author: Open edX Project
Author-email: oscm@openedx.org
License: Apache 2.0
Keywords: Python edx
Classifier: Development Status :: 3 - Alpha
Classifier: Framework :: Django
Classifier: Framework :: Django :: 4.2
Classifier: Framework :: Django :: 5.2
Classifier: Intended Audience :: Developers
Classifier: License :: OSI Approved :: Apache Software License
Classifier: Natural Language :: English
Classifier: Programming Language :: Python :: 3
Classifier: Programming Language :: Python :: 3.11
Classifier: Programming Language :: Python :: 3.12
Requires-Python: >=3.11
License-File: LICENSE
Requires-Dist: Django
Requires-Dist: XBlock
Requires-Dist: celery
Requires-Dist: django_crum
Requires-Dist: djangorestframework
Requires-Dist: edx-django-utils
Requires-Dist: edx-opaque-keys
Requires-Dist: edx-toggles
Requires-Dist: openedx-atlas
Requires-Dist: openedx-filters
Requires-Dist: prison
Requires-Dist: redis
Requires-Dist: requests
Requires-Dist: superset-api-client
Requires-Dist: web_fragments
Dynamic: author
Dynamic: author-email
Dynamic: classifier
Dynamic: description
Dynamic: home-page
Dynamic: keywords
Dynamic: license
Dynamic: license-file
Dynamic: requires-dist
Dynamic: requires-python
Dynamic: summary
